sdx_topology_validator/__init__.py
sdx_topology_validator/topology_validator.py
sdx_topology_validator/validator.yaml
sdx_topology_validator-1.1.8.dist-info/METADATA
sdx_topology_validator-1.1.8.dist-info/WHEEL
sdx_topology_validator-1.1.8.dist-info/top_level.txt
sdx_topology_validator-1.1.8.dist-info/RECORD
